nonebot_plugin_custom_face/__init__.py
nonebot_plugin_custom_face-0.1.1.dist-info/LICENSE
nonebot_plugin_custom_face-0.1.1.dist-info/METADATA
nonebot_plugin_custom_face-0.1.1.dist-info/WHEEL
nonebot_plugin_custom_face-0.1.1.dist-info/RECORD
