Metadata-Version: 2.3
Name: nonebot-plugin-custom-face
Version: 0.1.1
Summary: 提供了关于QQ自定义表情的API
License: MIT
Author: BG4JEC
Author-email: BG4JEC@hotmail.com
Requires-Python: >=3.9,<4.0
Classifier: License :: OSI Approved :: MIT License
Classifier: Programming Language :: Python :: 3
Classifier: Programming Language :: Python :: 3.9
Classifier: Programming Language :: Python :: 3.10
Classifier: Programming Language :: Python :: 3.11
Classifier: Programming Language :: Python :: 3.12
Classifier: Programming Language :: Python :: 3.13
Requires-Dist: nonebot-adapter-onebot (>=2.2.2,<3.0.0)
Requires-Dist: nonebot-plugin-localstore (>=0.7.3,<0.8.0)
Requires-Dist: nonebot2[fastapi] (>=2.3.0,<3.0.0)
Project-URL: Repository, https://github.com/2580m/nonebot-plugin-custom-face
